rtl/constants.v
// contants.v contains project wide defines and macros

// alu ops
`define OP_SUM  3'd0
`define OP_SUB  3'd1
`define OP_AND  3'd2
`define OP_OR   3'd3
`define OP_LSL  3'd4
`define OP_LSR  3'd5
`define OP_NOT  3'd6
`define OP_ID  3'd7

// ALU flag positions
`define FLAG_CARRY      0
`define FLAG_NEGATIVE   1
`define FLAG_OVERFLOW   2
`define FLAG_ZERO       3
`define FLAG_PARITY     4

// defaults for dibu
`define DATA_WORD_SIZE 8
`define DATA_ADDR_SIZE 10

// jump types
`define JMP 3'b000
`define JE 3'b001
`define JNE 3'b010
`define JN 3'b011

rtl/alu.v
`timescale 1ns / 1ps

`include "constants.v"

// alu implements an 8-bit ALU.
module alu(
    a,
    b,
    op,
    out,
    flags
    );
    
    // INPUTS
    
    // a is the 8bit first operand. 
    // Whenever the operation uses just one operand, a should be used
    input [7:0] a;
    // b is the 8bit first operand
    input [7:0] b;
    // op, selector de funcion de alu
    // todo(pablo): renombrar por func
    input [2:0] op;
    
    // OUTPUTS
    
    // out is the 8bit alu out
    output reg [7:0] out;
    // flags is the 8bit flags out
    output [7:0] flags;
    
    // INTERNAL VARS
    
    wire zero, negative, parity, overflow;
    reg carry;
    
    // COMBINATIONAL LOGIC
    
    assign flags = {3'd0, parity, zero, overflow, negative, carry};
    
    // combinatory flags
    // invert all bits, if all zero it will be 8'b1*, then and bit by bit
    assign zero = &(~out);
    // operadores en ca2, bit mas significativo es signo
    assign negative = out[7];
    // https://en.wikipedia.org/wiki/Parity_function
    assign parity = ~(^out);
    
    // if it's substraction, use the same overflow logic but apply
    // the negative sign to be before, so that a - b => a + (-b)
    wire [7:0] maybe_negated_b = op == `OP_SUB ? (~b + 1) : b;
    assign overflow =
        (a[7] ~^ maybe_negated_b[7]) // si los dos operando tienen el mismo signo
        & (a[7] != out[7]); // y la salida tiene signo diferente, dio la vuelta
    
    always @ (*) begin
        case (op)
            `OP_SUM: begin
                {carry, out} <= a + b;
            end
            `OP_SUB: begin
                out <= a - b;
                carry <= 0;
            end
            `OP_AND: begin
                out <= a & b;
                carry <= 0;
            end
            `OP_OR: begin
                out <= a | b;
                carry <= 0;
            end
            `OP_NOT: begin
                out <= ~a;
                carry <= 0;
            end
            `OP_LSL: begin
                out <= a << b;
                carry <= 0;
            end
            `OP_LSR: begin
                out <= a >> b;
                carry <= 0;
            end
            default begin
                $display("unsupported alu op: %b", op);
                carry <= 0;
                out <= 0;
            end
        endcase
    end
endmodule

rtl/register.v
`timescale 1ns / 1ps
//////////////////////////////////////////////////////////////////////////////////
// Company: 
// Engineer: 
// 
// Create Date: 06/12/2023 10:06:50 PM
// Design Name: 
// Module Name: register
// Project Name: 
// Target Devices: 
// Tool Versions: 
// Description: 
// 
// Dependencies: 
// 
// Revision:
// Revision 0.01 - File Created
// Additional Comments:
// 
//////////////////////////////////////////////////////////////////////////////////


module register #(parameter width=8) (clk, w_en, d_in, d_out);
    input clk;
    // w_en: write enable
    input w_en;
    // d_in: data in, will be written in next posedge when w_en high
    input [width-1:0] d_in;

    // d_out: data out
    output reg [width-1:0] d_out;

    initial d_out <= 0;

    always @ (posedge clk) begin
        if (w_en)
            d_out <= d_in;
    end

endmodule

rtl/register_bank.v
`timescale 1ns / 1ps
//
// register_bank is the DiBU main register bank. ri_* are the registers index.
// a, b are the read registers, and d is the input for writing a register.
// Two registers can be read at the same time, but only one can be written.
//
module register_bank(clk, ri_a, ri_b, ri_d, rw, d, a, b);
    // clk is the main clock signal
    input wire clk;
    // rw selects if the register write or read on posedge of clk.
    // rw == 0: READ
    // rw == 1: WRITE
    input wire rw;
    // ri_* are the register index
    input [2:0] ri_a, ri_b, ri_d;
    // d is the write date
    input [7:0] d;
    // a, b are the registers out
    output reg [7:0] a, b;

    reg [7:0] bank [0:7];

    integer i;
    initial begin
        for (i = 0; i < 7; i=i+1) begin
            bank[i] = 8'd0;
        end
    end

    always @ (posedge clk) begin
        if (rw) begin
            // write
            bank[ri_d] <= d;
        end else begin
            // read
            a <= bank[ri_a];
            b <= bank[ri_b];
        end
    end
endmodule

rtl/control_unit.v
`timescale 1ns / 1ps

`include "constants.v"

module ctrl_unit(clk, opcode, signals);
    // clk: clock signal
    input clk;
    // opcode, which corresponds to the ir[15:11] bits
    input [4:0] opcode;
    // signals: output signals from the contorl unit
    output [4:0] signals;

    // todo: parametrize this por favor
    reg [`store_word_size-1:0] store [0:7];
    // next_addr are the address bits from the microsintruction
    wire [`micro_addr_size-1:0] next_addr;
    // chosen next address is the output of the microsequencer block
    reg [`micro_addr_size-1:0] chosen_next_addr;
    // bit should be set if we are on the decision state, aka
    // the state where the control unit decides which instruction is being executed
    wire is_decision_state;

    // current is the current microinstruction
    reg [`store_word_size-1:0] current;

    // combinational block
    assign is_decision_state = current[0];
    assign signals = current[`signals_size:1];
    assign next_addr = current[`store_word_size-1:`store_word_size-`micro_addr_size];

    integer i;

    // load microprogram in rom
    initial begin
        $display("reading microprogram into store");
        $readmemb("/home/pablo/facultad/fpga/dibu-architecture/rtl/microprogram_clean.mem", store);
        for (i=0;i<=7;i=i+1) 
            $display("micro addr=%d instr=%b", i, store[i]);
        current = 'd0;
    end

    // todo(pablo): maybe extract
    // microsequencer block
    always @ (*) begin
        if (is_decision_state) begin
            casex (opcode) 
                // mov r1 r2
                5'b00111: chosen_next_addr <= `micro_addr_size'd2;
                // mov r1 imm
                5'b01000: chosen_next_addr <= `micro_addr_size'd6;
                // alu operations
                5'b00???: chosen_next_addr <= `micro_addr_size'd4;
                default: begin
                    $display("unsupported instruction: %b", opcode);
                    // if not supported, go to fetch
                    chosen_next_addr <= `micro_addr_size'd0;
                end
            endcase
        end else
            // base case, where each microinstruction decides it's next addr
            chosen_next_addr <= next_addr;
    end

    // sequential block
    always @ (posedge clk) begin
        current <= store[chosen_next_addr];
        $display("microinstr: %h", chosen_next_addr);
    end
endmodule

rtl/memory.v
`timescale 1ns / 1ps

`include "constants.v"

module memory_bank #(
    parameter word_size=`DATA_WORD_SIZE,
    parameter addr_size=`DATA_ADDR_SIZE
) (
    clk,
    w_en,
    addr,
    d_in,
    d_out,
);
    // clk: clock signal
    // w_en: write enable
    input clk, w_en;

    // addr: address for read/write operations
    input [addr_size-1:0] addr;
    // d_in: data in
    input [word_size-1:0] d_in;

    // d_out: data out
    output reg [word_size-1:0] d_out;

    // main memory bank
    reg [word_size-1:0] bank [0:(2 ** addr_size)-1];

    assign d_out = bank[addr];

    always @ (posedge clk) begin
        if (w_en)
            bank[addr] <= d_in;
    end
endmodule

rtl/datapath.v
`timescale 1ns / 1ps

`include "constants.v"

module datapath(clk, run, code_w_en, code_addr_in, code_in, debug);
    input clk;
    //code_w_en: enable write to code memory
    //run: enable run processor
    input code_w_en;
    input run;
    //code_in: code input
    input [15:0] code_in;
    // code_addr_in: code address in
    input [8:0] code_addr_in;
    reg zero;
    reg [15:0] big_zero;
    output [7:0] debug;
    
    initial begin
        zero = 0;
        big_zero = 15'd0;
        // program initials
        // the "macro" to dump signals
        `ifdef COCOTB_SIM
        $dumpfile ("datapath.vcd");
        $dumpvars (0, datapath);
        #1;
        `endif
    end
    

    //
    // control signals
    //
    // signals are the control unit signals wire
    wire [`signals_size-1:0] signals;

    // control if the pc should be incremented in next rising edge
    wire pc_inc;
    assign pc_inc = signals[0];
    // control if memory address register should be writtenn 
    wire mar_w_en;
    assign mar_w_en = signals[1];
    // control if register bank should read or write
    // 0 read
    // 1 write
    wire reg_rw;
    assign reg_rw = signals[2];
    // control if register data in should be alu out or immediate from ir
    // 0 alu
    // 1 immediatcode_w_ene
    wire reg_select_in;
    assign reg_select_in = signals[3];
    // control if the flags should be written from the alu
    wire flags_w_en;
    assign flags_w_en = signals[4];

    
    // pc: program counter
    wire [8:0] pc_write_in;
    assign pc_write_in = pc_inc ? pc+1 : pc;
    wire [8:0] pc;
    register #(9) pc_register(
        .clk(clk),
        .w_en(pc_inc),
        .d_in(pc_write_in),
        .d_out(pc)
    );

    // mar: memory address register
    wire [8:0] mar;
    register #(9) mar_register(
        .clk(clk),
        .w_en(mar_w_en),
        .d_in(pc),
        .d_out(mar)
    );
    
    //
    // code memory
    //
    
    // ir: instruction register
    wire [15:0] ir;

    always @ (posedge clk) $display("el ir es: %h", ir);

    memory_bank #(16, 9) code_mem(
        .clk(clk),
        .w_en(code_w_en),
        .addr(code_w_en ? code_addr_in : mar),
        .d_in(code_in),
        .d_out(ir)
    );

    // immediate: immediate word-sized operand from instruction format
    wire [7:0] immediate;
    assign immediate = ir[7:0];
    
    wire [7:0] alu_out, alu_a, alu_b, alu_flags, flags;
    wire [7:0] reg_data_in;

    assign debug = alu_out;
    
    assign reg_data_in = reg_select_in ? immediate : alu_out; 

    // control unit
    ctrl_unit control(
        .clk(clk & run),
        .opcode(ir[15:11]),
        .signals(signals)
    );

    // processing data path

    register_bank rbank(
        .clk(clk),
        .ri_a(ir[5:3]),
        .ri_b(ir[2:0]),
        .ri_d(ir[10:8]),
        .rw(reg_rw),
        .d(reg_data_in),
        .a(alu_a),
        .b(alu_b)
    );

    register flags_register(
        .clk(clk),
        .w_en(flags_w_en),
        .d_in(alu_flags),
        .d_out(flags)
    );

    alu alu_unit(
        .a(alu_a),
        .b(alu_b),
        .out(alu_out),
        .flags(alu_flags),
        .op(ir[13:11])
    );

endmodule

rtl_tests/datapath.vcd
$date
	Tue Jun 13 22:47:21 2023
$end
$version
	Icarus Verilog
$end
$timescale
	1ps
$end
$scope module datapath $end
$var wire 1 ! clk $end
$var wire 9 " code_addr_in [8:0] $end
$var wire 16 # code_in [15:0] $end
$var wire 1 $ code_w_en $end
$var wire 8 % debug [7:0] $end
$var wire 1 & run $end
$var wire 5 ' signals [4:0] $end
$var wire 1 ( reg_select_in $end
$var wire 1 ) reg_rw $end
$var wire 8 * reg_data_in [7:0] $end
$var wire 9 + pc_write_in [8:0] $end
$var wire 1 , pc_inc $end
$var wire 9 - pc [8:0] $end
$var wire 1 . mar_w_en $end
$var wire 9 / mar [8:0] $end
$var wire 16 0 ir [15:0] $end
$var wire 8 1 immediate [7:0] $end
$var wire 1 2 flags_w_en $end
$var wire 8 3 flags [7:0] $end
$var wire 8 4 alu_out [7:0] $end
$var wire 8 5 alu_flags [7:0] $end
$var wire 8 6 alu_b [7:0] $end
$var wire 8 7 alu_a [7:0] $end
$var reg 16 8 big_zero [15:0] $end
$var reg 1 9 zero $end
$scope module alu_unit $end
$var wire 3 : op [2:0] $end
$var wire 1 ; overflow $end
$var wire 1 < parity $end
$var wire 1 = zero $end
$var wire 1 > negative $end
$var wire 8 ? maybe_negated_b [7:0] $end
$var wire 8 @ flags [7:0] $end
$var wire 8 A b [7:0] $end
$var wire 8 B a [7:0] $end
$var reg 1 C carry $end
$var reg 8 D out [7:0] $end
$upscope $end
$scope module code_mem $end
$var wire 9 E addr [8:0] $end
$var wire 1 ! clk $end
$var wire 16 F d_in [15:0] $end
$var wire 1 $ w_en $end
$var reg 16 G d_out [15:0] $end
$upscope $end
$scope module control $end
$var wire 1 H clk $end
$var wire 5 I opcode [4:0] $end
$var wire 5 J signals [4:0] $end
$var wire 3 K next_addr [2:0] $end
$var wire 1 L is_decision_state $end
$var reg 3 M chosen_next_addr [2:0] $end
$var reg 9 N current [8:0] $end
$var integer 32 O i [31:0] $end
$upscope $end
$scope module flags_register $end
$var wire 1 ! clk $end
$var wire 8 P d_in [7:0] $end
$var wire 1 2 w_en $end
$var reg 8 Q d_out [7:0] $end
$upscope $end
$scope module mar_register $end
$var wire 1 ! clk $end
$var wire 1 . w_en $end
$var wire 9 R d_in [8:0] $end
$var reg 9 S d_out [8:0] $end
$upscope $end
$scope module pc_register $end
$var wire 1 ! clk $end
$var wire 9 T d_in [8:0] $end
$var wire 1 , w_en $end
$var reg 9 U d_out [8:0] $end
$upscope $end
$scope module rbank $end
$var wire 1 ! clk $end
$var wire 8 V d [7:0] $end
$var wire 3 W ri_a [2:0] $end
$var wire 3 X ri_b [2:0] $end
$var wire 3 Y ri_d [2:0] $end
$var wire 1 ) rw $end
$var reg 8 Z a [7:0] $end
$var reg 8 [ b [7:0] $end
$var integer 32 \ i [31:0] $end
$upscope $end
$upscope $end
$enddefinitions $end
#0
$dumpvars
b1000 \
bx [
bx Z
bx Y
bx X
bx W
bx V
b0 U
b0 T
b0 S
b0 R
b0 Q
b0xxxxx P
b1000 O
b0 N
b0 M
0L
b0 K
b0 J
bx I
0H
bx G
bz F
b0 E
bx D
xC
bx B
bx A
b0xxxxx @
bx ?
x>
x=
x<
x;
bx :
09
b0 8
bx 7
bx 6
b0xxxxx 5
bx 4
b0 3
02
bx 1
bx 0
b0 /
0.
b0 -
0,
b0 +
bx *
0)
0(
b0 '
0&
bx %
0$
bz #
bz "
1!
$end
#5000
0!
#10000
1!
#15000
0!
#20000
1!
#25000
b100001111110000 #
b100001111110000 F
b0 "
1$
0!
#30000
1!
#35000
b1 E
b11110000011000 #
b11110000011000 F
b1 "
0!
#40000
1!
#45000
b10 E
b11010100100000 #
b11010100100000 F
b10 "
0!
#50000
1!
#55000
b0 E
1&
0$
0!
#60000
b1 M
b1 +
b1 T
1.
1,
b11 '
b11 J
b1 K
b0 :
b11 Y
b0 X
b110 W
b1000 I
b11110000 1
b1000110 N
b100001111110000 0
b100001111110000 G
1H
1!
#65000
0H
0!
#70000
0;
0>
1<
1=
b0 *
b0 V
b111 M
b11000 5
b11000 @
b11000 P
0C
b0 %
b0 4
b0 D
0.
0,
b0 '
b0 J
b111 K
b0 ?
b1 +
b1 T
b111000000 N
b0 6
b0 A
b0 [
b0 7
b0 B
b0 Z
b1 -
b1 R
b1 U
1H
1!
#75000
0H
0!
#80000
b110 M
1L
b0 K
b1 N
1H
1!
#85000
0H
0!
#90000
b0 M
b11110000 *
b11110000 V
1(
1)
0L
b1100 '
b1100 J
b11000 N
1H
1!
#95000
0H
0!
#100000
b1 M
b0 *
b0 V
b10 +
b10 T
0(
0)
1.
1,
b11 '
b11 J
b1 K
b1000110 N
1H
1!
#105000
0H
0!
#110000
b111 M
0.
0,
b0 '
b0 J
b111 K
b1 E
b10 +
b10 T
b111000000 N
b1 /
b1 S
b10 -
b10 R
b10 U
1H
1!
#115000
0H
0!
#120000
b10 M
1L
b0 K
b111 :
b100 Y
b11 W
b111 I
b11000 1
b1 N
b11110000011000 0
b11110000011000 G
1H
1!
#125000
0H
0!
#130000
1>
b10010 5
b10010 @
b10010 P
0=
b11110000 *
b11110000 V
b11 M
b11110000 %
b11110000 4
b11110000 D
0L
b11 K
b11000000 N
b11110000 7
b11110000 B
b11110000 Z
1H
1!
#135000
0H
0!
#140000
b0 M
1)
b100 '
b100 J
b0 K
b1000 N
1H
1!
#145000
0H
0!
#150000
b1 M
b11 +
b11 T
0)
1.
1,
b11 '
b11 J
b1 K
b1000110 N
1H
1!
#155000
0H
0!
#160000
b111 M
0.
0,
b0 '
b0 J
b111 K
b11 +
b11 T
b10 E
b111000000 N
b11 -
b11 R
b11 U
b10 /
b10 S
1H
1!
#165000
0H
0!
#170000
b10000 5
b10000 @
b10000 P
0>
b1111 *
b1111 V
b1111 %
b1111 4
b1111 D
b100 M
1L
b0 K
b110 :
b101 Y
b100 W
b110 I
b100000 1
b1 N
b11010100100000 0
b11010100100000 G
1H
1!
#175000
0H
0!
#180000
b101 M
0L
b101 K
b101000000 N
1H
1!
#185000
0H
0!
#190000
b0 M
12
1)
b10100 '
b10100 J
b0 K
b101000 N
1H
1!
#195000
0H
0!
#200000
b1 M
b100 +
b100 T
02
0)
1.
1,
b11 '
b11 J
b1 K
b1000110 N
b10000 3
b10000 Q
1H
1!
#205000
0H
0!
#210000
b111 M
0.
0,
b0 '
b0 J
b111 K
b11 E
b100 +
b100 T
b111000000 N
b11 /
b11 S
b100 -
b100 R
b100 U
1H
1!
#215000
0H
0!
#220000
b10 M
1L
b0 K
bx :
bx Y
bx X
bx W
bx I
bx 1
b1 N
bx 0
bx G
1H
1!
#225000
0H
0!
#230000
b11 M
b10x00 5
b10x00 @
b10x00 P
x;
0L
b11 K
bx ?
b11000000 N
bx 6
bx A
bx [
bx 7
bx B
bx Z
1H
1!
#235000
0H
0!
#240000
b0 M
1)
b100 '
b100 J
b0 K
b1000 N
1H
1!
#245000
0H
0!
#250000
b1 M
b101 +
b101 T
0)
1.
1,
b11 '
b11 J
b1 K
b1000110 N
1H
1!
